{
  "servers": {
    "sequentialthinking": {
      "type": "stdio",
      "command": "npx",
      "args": [
        "-y",
        "@modelcontextprotocol/server-sequential-thinking@latest"
      ],
      "gallery": true
    },
    "context7": {
      "type": "stdio",
      "command": "npx",
      "args": [
        "-y",
        "@upstash/context7-mcp@latest"
      ],
      "gallery": true
    },
    "deepwiki": {
      "type": "http",
      "url": "https://mcp.deepwiki.com/sse",
      "gallery": true
    },
    "git": {
      "command": "uvx",
      "args": [
        "mcp-server-git"
      ],
      "type": "stdio"
    },
    "time": {
      "command": "uvx",
      "args": [
        "mcp-server-time"
      ],
      "type": "stdio"
    },
    "memory": {
      "type": "stdio",
      "command": "npx",
      "args": [
        "-y",
        "@modelcontextprotocol/server-memory@latest"
      ],
      "env": {
        "MEMORY_FILE_PATH": "${workspaceFolder}/.vscode/memory.json"
      }
    }
  },
  "inputs": [],
  "$gorka": {
    "servers": [
      "context7",
      "deepwiki",
      "git",
      "memory",
      "sequentialthinking",
      "time"
    ],
    "inputs": []
  }
}
